{
  "dogs": [
    {
      "name": "Otilia",
      "image": "/assets/dalmation.png",
      "description": "Outdoors HDD World Granite plum",
      "isFavorite": true,
      "id": 1
    },
    {
      "name": "Annamae",
      "image": "/assets/chihuahua.avif",
      "description": "empower exciting Hat Card Music portals Ford",
      "isFavorite": false,
      "id": 3
    },
    {
      "name": "Linda",
      "image": "/assets/corgi.png",
      "description": "robust port Lamborghini Representative Jazz",
      "isFavorite": true,
      "id": 4
    },
    {
      "name": "Abdul",
      "image": "/assets/chihuahua.avif",
      "description": "program Keyboard Movies deposit azure South snob",
      "isFavorite": false,
      "id": 8
    },
    {
      "name": "Amos",
      "image": "/assets/cowardly.png",
      "description": "Electric Borders deploy World zowie Agender reboot",
      "isFavorite": true,
      "id": 9
    },
    {
      "name": "Ryan",
      "image": "/assets/chihuahua.avif",
      "description": "but Bronze tart Forward Diesel",
      "isFavorite": true,
      "id": 10
    },
    {
      "name": "Eleanore",
      "image": "/assets/dalmation.png",
      "description": "SUV Iron indigo SMS South",
      "isFavorite": true,
      "id": 11
    },
    {
      "name": "Constance",
      "image": "/assets/corgi.png",
      "description": "female Generic Recumbent Wooden ROI Borders dependent",
      "isFavorite": true,
      "id": 12
    },
    {
      "name": "Alexys",
      "image": "/assets/corgi.png",
      "description": "Computer Jaguar Rican Intelligent Card",
      "isFavorite": true,
      "id": 14
    },
    {
      "name": "Arielle",
      "image": "/assets/blue-heeler.png",
      "description": "West Ridges loyalty siemens North copying whack Wooden",
      "isFavorite": true,
      "id": 15
    },
    {
      "name": "Jadyn",
      "image": "/assets/corgi.png",
      "description": "Berkshire Jewelery engineer Bicycle South",
      "isFavorite": true,
      "id": 16
    },
    {
      "name": "Alysha",
      "image": "/assets/corgi.png",
      "description": "female Gasoline however architectures plain",
      "isFavorite": true,
      "id": 18
    },
    {
      "name": "another dog",
      "image": "/assets/boxer.jpeg",
      "description": "another description for boxer.",
      "isFavorite": true,
      "id": 21
    },
    {
      "name": "11:43",
      "image": "/assets/corgi.png",
      "description": "11:43 entry",
      "isFavorite": false,
      "id": 23
    },
    {
      "name": "11:43 second time",
      "image": "/assets/chihuahua.avif",
      "description": "another description.",
      "isFavorite": true,
      "id": 24
    },
    {
      "name": "Tuesday Dog",
      "image": "/assets/boxer.jpeg",
      "description": "My first class dog submission. Boxer.",
      "isFavorite": false,
      "id": 27
    },
    {
      "name": "8:12 pm ",
      "image": "/assets/dalmation.png",
      "description": "what you wanna do?",
      "isFavorite": false,
      "id": 28
    },
    {
      "name": "Thursday Dog",
      "image": "/assets/corgi.png",
      "description": "Trying a Thursday Dog.",
      "isFavorite": false,
      "id": 29
    },
    {
      "name": "adsfas",
      "image": "/assets/boxer.jpeg",
      "description": "fdasfads",
      "isFavorite": false,
      "id": 30
    },
    {
      "name": "Test 55",
      "image": "/assets/cowardly.png",
      "description": "55 tests.",
      "isFavorite": false,
      "id": 31
    },
    {
      "name": "66 Tonight",
      "image": "/assets/blue-heeler.png",
      "description": "Let's go 66.",
      "isFavorite": false,
      "id": 32
    },
    {
      "name": "2345",
      "image": "/assets/boxer.jpeg",
      "description": "5423",
      "isFavorite": false,
      "id": 33
    }
  ]
}